PotatosAioKafkaEngine/AioKafkaEngine.py
PotatosAioKafkaEngine/__init__.py
potatosaiokafkaengine-0.0.2.dist-info/METADATA
potatosaiokafkaengine-0.0.2.dist-info/WHEEL
potatosaiokafkaengine-0.0.2.dist-info/licenses/LICENSE
potatosaiokafkaengine-0.0.2.dist-info/RECORD
