Metadata-Version: 2.1
Name: PotatosAioKafkaEngine
Version: 0.0.2
Summary: Wrapper around aio-kafka to use and receive via a asyncio queue
Project-URL: Homepage, https://github.com/RusticPotatos/PotatosAioKafkaEngine
Project-URL: Bug Tracker, https://github.com/RusticPotatos/PotatosAioKafkaEngine/issues
Author-email: RusticPotatos <author@example.com>
License-File: LICENSE
Classifier: License :: OSI Approved :: MIT License
Classifier: Operating System :: OS Independent
Classifier: Programming Language :: Python :: 3
Requires-Python: >=3.10
